{
    "AL02": "uL2",
    "AL15": "uL15",
    "AL16": "uL16",
    "AL17": "bL17",
    "AL18": "uL18",
    "AL19": "bL19",
    "AL20": "bL20",
    "AL21": "bL21",
    "AL22": "uL22",
    "AL23": "uL23",
    "AL24": "uL24",
    "AL03": "uL3",
    "AL25": "bL25",
    "AL27": "bL27",
    "AL28": "bS6",
    "AL29": "uL29",
    "AL30": "uL30",
    "AL32": "bL32",
    "AL33": "bL33",
    "AL34": "bL34",
    "AL35": "bL35",
    "AS02": "uS2",
    "AL04": "uL4",
    "AS03": "uS3",
    "AS04": "uS4",
    "AS05": "uS5",
    "AS06": "bS6",
    "AS07": "uS7",
    "AS08": "uS8",
    "AS09": "uS9",
    "AS10": "uS10",
    "AS11": "uS11",
    "AS12": "uS12",
    "AL05": "uL5",
    "AS13": "uS13",
    "AS14": "uS14",
    "AS15": "uS15",
    "AS16": "bS16",
    "AS17": "uS17",
    "AS18": "bS18",
    "AS19": "uS19",
    "AS20": "bS20",
    "ATHX": "bTHX",
    "AL31": "bL31",
    "AL06": "uL6",
    "AL09": "bL9",
    "AL11": "uL11",
    "AL13": "uL13",
    "AL14": "uL14"
}