{
    "D": "uL3",
    "Y": "bL28",
    "w": "uL29",
    "K": "uL13",
    "L": "uL14",
    "M": "uL15",
    "N": "uL16",
    "O": "bL17",
    "P": "uL18",
    "Q": "bL19",
    "R": "bL20",
    "S": "bL21",
    "T": "uL22",
    "U": "uL23",
    "V": "uL24",
    "W": "bL25",
    "X": "bL27",
    "Z": "uL29",
    "0": "uL30",
    "1": "bL32",
    "2": "bL33",
    "3": "bL34",
    "C": "uL2",
    "4": "bL35",
    "5": "bL36",
    "b": "uS2",
    "c": "uS3",
    "d": "uS4",
    "e": "uS5",
    "f": "bS6",
    "g": "uS7",
    "h": "uS8",
    "i": "uS9",
    "j": "uS10",
    "k": "uS11",
    "l": "uS12",
    "m": "uS13",
    "n": "uS14",
    "o": "uS15",
    "p": "bS16",
    "q": "uS17",
    "r": "bS18",
    "E": "uL4",
    "s": "uS19",
    "t": "bS20",
    "u": "bS21",
    "F": "uL5",
    "G": "uL6",
    "H": "bL9",
    "J": "uL11"
}