{
    "B1": "eL39",
    "C1": "eS1",
    "D1": "uS13",
    "E1": "uS7",
    "F1": "eS4",
    "I1": "eS7",
    "K1": "uS4",
    "L1": "eS10",
    "M1": "uL1",
    "N1": "eS12",
    "O1": "uS15",
    "Q1": "uS19",
    "R1": "uS9",
    "S1": "eS17",
    "T1": "uS13",
    "U1": "eS19",
    "V1": "uS10",
    "X1": "uS8",
    "Z1": "eS24",
    "a1": "eS25",
    "b1": "eS26",
    "c1": "eS27",
    "d1": "eS28",
    "e1": "uS14",
    "f1": "uS2",
    "g1": "eS31",
    "h1": "RACK1",
    "j1": "bL36",
    "k1": "uS10",
    "A3": "uL2",
    "B3": "uL3",
    "E3": "uS8",
    "F3": "uL30",
    "H3": "uL6",
    "L3": "eL13",
    "M3": "eL14",
    "N3": "eL15",
    "O3": "uL13",
    "P3": "bS21",
    "R3": "eL19",
    "S3": "eL20",
    "T3": "eL21",
    "V3": "uL14",
    "W3": "eL24",
    "X3": "uL10",
    "Y3": "uL24",
    "Z3": "eL27",
    "a3": "uL15",
    "b3": "uL3",
    "c3": "eL30",
    "d3": "eL31",
    "e3": "eL32",
    "f3": "eL33",
    "g3": "uL1",
    "h3": "uL10",
    "i3": "eL36",
    "k3": "eL38",
    "l3": "eL39",
    "m3": "uL1",
    "n3": "eL41",
    "p3": "eL43",
    "r3": "eL28",
    "s3": "bL35",
    "J3": "uL5",
    "G3": "uS10",
    "D3": "eL39",
    "I3": "uL16",
    "J1": "eS8",
    "P1": "bL34",
    "W1": "eS21",
    "Y1": "uS12",
    "C3": "eL39",
    "Q3": "eL18",
    "U3": "eL22",
    "G1": "uS2",
    "j3": "eL37",
    "o3": "eL42",
    "t3": "uL11",
    "H1": "eS6",
    "u3": "uL1"
}