{
    "LG": "eL8",
    "LH": "uL6",
    "LI": "uL16",
    "LJ": "uL5",
    "LL": "eL13",
    "LM": "eL14",
    "LN": "eL15",
    "LO": "uL13",
    "LP": "bS21",
    "LQ": "eL18",
    "LR": "eL19",
    "LS": "eL20",
    "LT": "eL21",
    "LU": "eL22",
    "LW": "eL24",
    "LX": "uL10",
    "LY": "uL24",
    "LZ": "eL27",
    "La": "uL15",
    "Lb": "eL29",
    "Lc": "eL30",
    "Ld": "eL31",
    "Le": "eL32",
    "Lf": "eL33",
    "Lg": "uL1",
    "Lh": "uL10",
    "Li": "eL36",
    "Lj": "eL37",
    "Lk": "eL38",
    "Ll": "eL39",
    "LA": "uL2",
    "Lm": "eL40",
    "Lo": "eL42",
    "Lp": "eL43",
    "Lr": "eL28",
    "A": "eL39",
    "LB": "uL3",
    "LC": "eL39",
    "LD": "eL39",
    "LE": "uS8",
    "LF": "uL30"
}