{
    "B": "uS2",
    "D": "uS5",
    "E": "uS3",
    "G": "uS7",
    "g": "eS31",
    "I": "eS7",
    "L": "eS10",
    "S": "eS17",
    "T": "uS13",
    "F": "uL30",
    "M": "eS4",
    "O": "uS17",
    "c": "uS12",
    "H": "eS6",
    "h": "RACK1",
    "J": "eS8",
    "K": "uS4",
    "N": "eS12",
    "Q": "uS19",
    "a": "eS25",
    "R": "uS9",
    "U": "eS19",
    "V": "uS10",
    "W": "eS21",
    "Z": "eS24",
    "P": "uS15",
    "X": "uS11",
    "Y": "uS8",
    "e": "eS27",
    "b": "eS26",
    "C": "eS1",
    "d": "eS28",
    "f": "eS30"
}