{
    "J1": "uS10",
    "K1": "uS11",
    "L1": "uS12",
    "M1": "uS13",
    "N1": "uS14",
    "O1": "uS15",
    "P1": "bS16",
    "Q1": "uS17",
    "R1": "bS18",
    "S1": "uS19",
    "B1": "uS2",
    "T1": "bS20",
    "U1": "bS21",
    "C2": "uL2",
    "D2": "uL3",
    "E2": "uL4",
    "F2": "uL5",
    "G2": "uL6",
    "H2": "uL10",
    "C1": "uS3",
    "I2": "uL11",
    "J2": "uL13",
    "K2": "uL14",
    "L2": "uL15",
    "M2": "uL16",
    "N2": "bL17",
    "O2": "uL18",
    "P2": "bL19",
    "Q2": "bL20",
    "R2": "bL21",
    "D1": "uS4",
    "S2": "uL22",
    "T2": "uL23",
    "U2": "uL24",
    "V2": "bL25",
    "W2": "bL27",
    "X2": "bL28",
    "Y2": "uL29",
    "Z2": "uL30",
    "a2": "bL32",
    "b2": "bL33",
    "E1": "uS5",
    "c2": "bL34",
    "d2": "bL35",
    "e2": "bL36",
    "F1": "bS6",
    "G1": "uS7",
    "H1": "uS8",
    "I1": "uS9"
}