{
    "BA": {
        "2576": {
            "P": [
                78.94599914550781,
                -61.25299835205078,
                6.040999889373779
            ],
            "OP1": [
                78.59400177001953,
                -62.10100173950195,
                4.894999980926514
            ],
            "OP2": [
                80.20700073242188,
                -60.48500061035156,
                5.98799991607666
            ],
            "O5'": [
                77.74700164794922,
                -60.229000091552734,
                6.2870001792907715
            ],
            "C5'": [
                76.47200012207031,
                -60.685001373291016,
                6.723999977111816
            ],
            "C4'": [
                75.36499786376953,
                -60.14400100708008,
                5.854000091552734
            ],
            "O4'": [
                75.55599975585938,
                -58.72700119018555,
                5.676000118255615
            ],
            "C3'": [
                75.29100036621094,
                -60.70899963378906,
                4.439000129699707
            ],
            "O3'": [
                74.50299835205078,
                -61.88199996948242,
                4.376999855041504
            ],
            "C2'": [
                74.69000244140625,
                -59.57400131225586,
                3.618000030517578
            ],
            "O2'": [
                73.27200317382812,
                -59.659000396728516,
                3.5989999771118164
            ],
            "C1'": [
                75.11199951171875,
                -58.327999114990234,
                4.4019999504089355
            ],
            "N9": [
                76.15899658203125,
                -57.53300094604492,
                3.73799991607666
            ],
            "C8": [
                76.11699676513672,
                -56.17399978637695,
                3.569999933242798
            ],
            "N7": [
                77.15899658203125,
                -55.6879997253418,
                2.9660000801086426
            ],
            "C5": [
                77.9489974975586,
                -56.79800033569336,
                2.7209999561309814
            ],
            "C6": [
                79.21099853515625,
                -56.9010009765625,
                2.0859999656677246
            ],
            "O6": [
                79.8949966430664,
                -56.000999450683594,
                1.6059999465942383
            ],
            "N1": [
                79.67400360107422,
                -58.21099853515625,
                2.0369999408721924
            ],
            "C2": [
                78.99400329589844,
                -59.292999267578125,
                2.546999931335449
            ],
            "N2": [
                79.5719985961914,
                -60.49700164794922,
                2.4170000553131104
            ],
            "N3": [
                77.81700134277344,
                -59.20600128173828,
                3.140000104904175
            ],
            "C4": [
                77.3479995727539,
                -57.944000244140625,
                3.190999984741211
            ]
        },
        "2577": {
            "P": [
                75.10700225830078,
                -63.233001708984375,
                3.7809998989105225
            ],
            "OP1": [
                75.84200286865234,
                -63.74700164794922,
                4.945000171661377
            ],
            "OP2": [
                75.72599792480469,
                -62.979000091552734,
                2.4639999866485596
            ],
            "O5'": [
                73.85800170898438,
                -64.2040023803711,
                3.572000026702881
            ],
            "C5'": [
                72.5719985961914,
                -63.70100021362305,
                3.252000093460083
            ],
            "C4'": [
                71.64800262451172,
                -64.7760009765625,
                2.7249999046325684
            ],
            "O4'": [
                72.26799774169922,
                -65.47799682617188,
                1.61899995803833
            ],
            "C3'": [
                71.26699829101562,
                -65.87899780273438,
                3.694999933242798
            ],
            "O3'": [
                70.22899627685547,
                -65.48600006103516,
                4.573999881744385
            ],
            "C2'": [
                70.87799835205078,
                -67.01699829101562,
                2.763000011444092
            ],
            "O2'": [
                69.56800079345703,
                -66.8239974975586,
                2.255000114440918
            ],
            "C1'": [
                71.87200164794922,
                -66.82499694824219,
                1.6169999837875366
            ],
            "N9": [
                73.06999969482422,
                -67.66600036621094,
                1.7790000438690186
            ],
            "C8": [
                74.25299835205078,
                -67.33300018310547,
                2.378000020980835
            ],
            "N7": [
                75.13099670410156,
                -68.30500030517578,
                2.38100004196167
            ],
            "C5": [
                74.48899841308594,
                -69.3550033569336,
                1.7369999885559082
            ],
            "C6": [
                74.87999725341797,
                -70.67400360107422,
                1.4229999780654907
            ],
            "N6": [
                76.07099914550781,
                -71.20899963378906,
                1.7130000591278076
            ],
            "N1": [
                73.97699737548828,
                -71.45700073242188,
                0.7870000004768372
            ],
            "C2": [
                72.77400207519531,
                -70.9489974975586,
                0.4869999885559082
            ],
            "N3": [
                72.29199981689453,
                -69.73699951171875,
                0.7319999933242798
            ],
            "C4": [
                73.20800018310547,
                -68.9739990234375,
                1.3660000562667847
            ]
        },
        "2578": {
            "P": [
                70.0770034790039,
                -66.14199829101562,
                6.034999847412109
            ],
            "OP1": [
                70.06500244140625,
                -67.61699676513672,
                5.894000053405762
            ],
            "OP2": [
                68.93299865722656,
                -65.46099853515625,
                6.673999786376953
            ],
            "O5'": [
                71.41200256347656,
                -65.77300262451172,
                6.828999996185303
            ],
            "C5'": [
                71.93299865722656,
                -64.4530029296875,
                6.849999904632568
            ],
            "C4'": [
                71.44599914550781,
                -63.683998107910156,
                8.050000190734863
            ],
            "O4'": [
                72.31800079345703,
                -63.89500045776367,
                9.192000389099121
            ],
            "C3'": [
                71.41999816894531,
                -62.176998138427734,
                7.896999835968018
            ],
            "O3'": [
                70.32099914550781,
                -61.72999954223633,
                7.125999927520752
            ],
            "C2'": [
                71.40299987792969,
                -61.70800018310547,
                9.343999862670898
            ],
            "O2'": [
                70.11199951171875,
                -61.83100128173828,
                9.90999984741211
            ],
            "C1'": [
                72.31700134277344,
                -62.74300003051758,
                10.005999565124512
            ],
            "N9": [
                73.68800354003906,
                -62.22999954223633,
                10.128000259399414
            ],
            "C8": [
                74.8499984741211,
                -62.68299865722656,
                9.555000305175781
            ],
            "N7": [
                75.88800048828125,
                -61.95600128173828,
                9.878999710083008
            ],
            "C5": [
                75.37799835205078,
                -60.972999572753906,
                10.708999633789062
            ],
            "C6": [
                76.01399993896484,
                -59.90399932861328,
                11.375
            ],
            "O6": [
                77.20600128173828,
                -59.595001220703125,
                11.366999626159668
            ],
            "N1": [
                75.11199951171875,
                -59.14899826049805,
                12.118000030517578
            ],
            "C2": [
                73.7699966430664,
                -59.39400100708008,
                12.210000038146973
            ],
            "N2": [
                73.06600189208984,
                -58.55400085449219,
                12.967000007629395
            ],
            "N3": [
                73.16300201416016,
                -60.3849983215332,
                11.598999977111816
            ],
            "C4": [
                74.0199966430664,
                -61.125,
                10.869000434875488
            ]
        },
        "2579": {
            "P": [
                70.49700164794922,
                -60.53799819946289,
                6.070000171661377
            ],
            "OP1": [
                69.5719985961914,
                -60.768001556396484,
                4.941999912261963
            ],
            "OP2": [
                71.91999816894531,
                -60.28099822998047,
                5.7769999504089355
            ],
            "O5'": [
                69.99299621582031,
                -59.28799819946289,
                6.895999908447266
            ],
            "C5'": [
                68.8550033569336,
                -59.39500045776367,
                7.73199987411499
            ],
            "C4'": [
                68.84200286865234,
                -58.2859992980957,
                8.743000030517578
            ],
            "O4'": [
                69.82599639892578,
                -58.569000244140625,
                9.774999618530273
            ],
            "C3'": [
                69.25900268554688,
                -56.922000885009766,
                8.227999687194824
            ],
            "O3'": [
                68.25499725341797,
                -56.25299835205078,
                7.484000205993652
            ],
            "C2'": [
                69.68000030517578,
                -56.23099899291992,
                9.513999938964844
            ],
            "O2'": [
                68.54499816894531,
                -55.94200134277344,
                10.312000274658203
            ],
            "C1'": [
                70.43499755859375,
                -57.36399841308594,
                10.196000099182129
            ],
            "N1": [
                71.86399841308594,
                -57.375999450683594,
                9.782999992370605
            ],
            "C2": [
                72.76200103759766,
                -56.47200012207031,
                10.378000259399414
            ],
            "O2": [
                72.35900115966797,
                -55.689998626708984,
                11.25100040435791
            ],
            "N3": [
                74.05699920654297,
                -56.45600128173828,
                9.993000030517578
            ],
            "C4": [
                74.47699737548828,
                -57.30099868774414,
                9.057000160217285
            ],
            "N4": [
                75.76300048828125,
                -57.249000549316406,
                8.720999717712402
            ],
            "C5": [
                73.60099792480469,
                -58.237998962402344,
                8.430999755859375
            ],
            "C6": [
                72.31999969482422,
                -58.237998962402344,
                8.821999549865723
            ]
        },
        "2580": {
            "P": [
                68.64299774169922,
                -55.25,
                6.285999774932861
            ],
            "OP1": [
                67.37200164794922,
                -54.78200149536133,
                5.679999828338623
            ],
            "OP2": [
                69.63400268554688,
                -55.86199951171875,
                5.375999927520752
            ],
            "O5'": [
                69.2699966430664,
                -54.000999450683594,
                7.033999919891357
            ],
            "C5'": [
                68.55000305175781,
                -53.35100173950195,
                8.069999694824219
            ],
            "C4'": [
                69.40799713134766,
                -52.334999084472656,
                8.77299976348877
            ],
            "O4'": [
                70.60700225830078,
                -52.98099899291992,
                9.258999824523926
            ],
            "C3'": [
                69.89900207519531,
                -51.18600082397461,
                7.8979997634887695
            ],
            "O3'": [
                68.99800109863281,
                -50.09600067138672,
                7.942999839782715
            ],
            "C2'": [
                71.24099731445312,
                -50.810001373291016,
                8.5
            ],
            "O2'": [
                71.04499816894531,
                -49.823001861572266,
                9.49899959564209
            ],
            "C1'": [
                71.70500183105469,
                -52.12099838256836,
                9.14900016784668
            ],
            "N1": [
                72.73100280761719,
                -52.83700180053711,
                8.380000114440918
            ],
            "C2": [
                74.04000091552734,
                -52.417999267578125,
                8.470000267028809
            ],
            "O2": [
                74.38400268554688,
                -51.444000244140625,
                9.121000289916992
            ],
            "N3": [
                74.91600036621094,
                -53.176998138427734,
                7.74399995803833
            ],
            "C4": [
                74.61599731445312,
                -54.28099822998047,
                6.980999946594238
            ],
            "O4": [
                75.51300048828125,
                -54.861000061035156,
                6.38100004196167
            ],
            "C5": [
                73.24199676513672,
                -54.652000427246094,
                6.965000152587891
            ],
            "C6": [
                72.36499786376953,
                -53.935001373291016,
                7.6539998054504395
            ]
        },
        "2581": {
            "P": [
                68.49400329589844,
                -49.374000549316406,
                6.609000205993652
            ],
            "OP1": [
                67.66400146484375,
                -48.249000549316406,
                7.078000068664551
            ],
            "OP2": [
                67.95999908447266,
                -50.41600036621094,
                5.691999912261963
            ],
            "O5'": [
                69.8030014038086,
                -48.76100158691406,
                5.949999809265137
            ],
            "C5'": [
                70.55999755859375,
                -47.766998291015625,
                6.618000030517578
            ],
            "C4'": [
                71.85900115966797,
                -47.49599838256836,
                5.9079999923706055
            ],
            "O4'": [
                72.69999694824219,
                -48.680999755859375,
                5.979000091552734
            ],
            "C3'": [
                71.74299621582031,
                -47.12900161743164,
                4.421999931335449
            ],
            "O3'": [
                72.56099700927734,
                -46.00400161743164,
                4.123000144958496
            ],
            "C2'": [
                72.27899932861328,
                -48.36899948120117,
                3.7049999237060547
            ],
            "O2'": [
                72.8949966430664,
                -48.12099838256836,
                2.4600000381469727
            ],
            "C1'": [
                73.2760009765625,
                -48.9119987487793,
                4.7179999351501465
            ],
            "N9": [
                73.56400299072266,
                -50.33700180053711,
                4.5370001792907715
            ],
            "C8": [
                74.81500244140625,
                -50.89400100708008,
                4.415999889373779
            ],
            "N7": [
                74.802001953125,
                -52.180999755859375,
                4.205999851226807
            ],
            "C5": [
                73.45500183105469,
                -52.49599838256836,
                4.160999774932861
            ],
            "C6": [
                72.82099914550781,
                -53.742000579833984,
                3.9549999237060547
            ],
            "O6": [
                73.33000183105469,
                -54.85200119018555,
                3.7660000324249268
            ],
            "N1": [
                71.44499969482422,
                -53.61600112915039,
                3.9820001125335693
            ],
            "C2": [
                70.75199890136719,
                -52.45899963378906,
                4.178999900817871
            ],
            "N2": [
                69.41100311279297,
                -52.56800079345703,
                4.171000003814697
            ],
            "N3": [
                71.3290023803711,
                -51.2869987487793,
                4.369999885559082
            ],
            "C4": [
                72.67500305175781,
                -51.37099838256836,
                4.349999904632568
            ]
        },
        "2582": {
            "P": [
                71.97599792480469,
                -44.520999908447266,
                4.341000080108643
            ],
            "OP1": [
                70.50299835205078,
                -44.6349983215332,
                4.440999984741211
            ],
            "OP2": [
                72.56800079345703,
                -43.58599853515625,
                3.374000072479248
            ],
            "O5'": [
                72.55000305175781,
                -44.0629997253418,
                5.75600004196167
            ],
            "C5'": [
                72.61399841308594,
                -42.6879997253418,
                6.107999801635742
            ],
            "C4'": [
                73.93699645996094,
                -42.31999969482422,
                6.739999771118164
            ],
            "O4'": [
                74.23100280761719,
                -43.22700119018555,
                7.843999862670898
            ],
            "C3'": [
                75.16300201416016,
                -42.404998779296875,
                5.835000038146973
            ],
            "O3'": [
                75.34500122070312,
                -41.233001708984375,
                5.047999858856201
            ],
            "C2'": [
                76.29000091552734,
                -42.64699935913086,
                6.829999923706055
            ],
            "O2'": [
                76.63500213623047,
                -41.43199920654297,
                7.47599983215332
            ],
            "C1'": [
                75.60099792480469,
                -43.55799865722656,
                7.85099983215332
            ],
            "N9": [
                75.70800018310547,
                -44.981998443603516,
                7.4679999351501465
            ],
            "C8": [
                74.64800262451172,
                -45.82699966430664,
                7.243000030517578
            ],
            "N7": [
                75.00399780273438,
                -47.02799987792969,
                6.894999980926514
            ],
            "C5": [
                76.38899993896484,
                -46.97700119018555,
                6.879000186920166
            ],
            "C6": [
                77.33399963378906,
                -47.98400115966797,
                6.565999984741211
            ],
            "O6": [
                77.125,
                -49.15299987792969,
                6.230000019073486
            ],
            "N1": [
                78.63800048828125,
                -47.513999938964844,
                6.677999973297119
            ],
            "C2": [
                78.98999786376953,
                -46.23500061035156,
                7.041999816894531
            ],
            "N2": [
                80.30000305175781,
                -45.95500183105469,
                7.0970001220703125
            ],
            "N3": [
                78.11900329589844,
                -45.29499816894531,
                7.331999778747559
            ],
            "C4": [
                76.84400177001953,
                -45.724998474121094,
                7.229000091552734
            ]
        },
        "2583": {
            "P": [
                75.84200286865234,
                -41.323001861572266,
                3.5179998874664307
            ],
            "OP1": [
                75.74099731445312,
                -39.974998474121094,
                2.9130001068115234
            ],
            "OP2": [
                75.177001953125,
                -42.457000732421875,
                2.8420000076293945
            ],
            "O5'": [
                77.3740005493164,
                -41.71799850463867,
                3.63700008392334
            ],
            "C5'": [
                78.30999755859375,
                -40.86800003051758,
                4.27400016784668
            ],
            "C4'": [
                79.63500213623047,
                -41.56399917602539,
                4.40500020980835
            ],
            "O4'": [
                79.43299865722656,
                -42.82500076293945,
                5.089000225067139
            ],
            "C3'": [
                80.2969970703125,
                -41.94300079345703,
                3.0889999866485596
            ],
            "O3'": [
                81.08200073242188,
                -40.88800048828125,
                2.568000078201294
            ],
            "C2'": [
                81.12300109863281,
                -43.16299819946289,
                3.4570000171661377
            ],
            "O2'": [
                82.33799743652344,
                -42.75699996948242,
                4.063000202178955
            ],
            "C1'": [
                80.24800109863281,
                -43.82400131225586,
                4.520999908447266
            ],
            "N9": [
                79.37200164794922,
                -44.89400100708008,
                3.994999885559082
            ],
            "C8": [
                78.00199890136719,
                -44.900001525878906,
                4.046000003814697
            ],
            "N7": [
                77.46800231933594,
                -45.979000091552734,
                3.5439999103546143
            ],
            "C5": [
                78.54900360107422,
                -46.74700164794922,
                3.1410000324249268
            ],
            "C6": [
                78.58799743652344,
                -48.0260009765625,
                2.5239999294281006
            ],
            "O6": [
                77.65599822998047,
                -48.76300048828125,
                2.190999984741211
            ],
            "N1": [
                79.88999938964844,
                -48.43299865722656,
                2.2880001068115234
            ],
            "C2": [
                81.01000213623047,
                -47.70600128173828,
                2.5989999771118164
            ],
            "N2": [
                82.177001953125,
                -48.2760009765625,
                2.2890000343322754
            ],
            "N3": [
                80.98699951171875,
                -46.52299880981445,
                3.1760001182556152
            ],
            "C4": [
                79.73100280761719,
                -46.09600067138672,
                3.4179999828338623
            ]
        },
        "2584": {
            "P": [
                81.0,
                -40.481998443603516,
                1.0190000534057617
            ],
            "OP1": [
                81.89800262451172,
                -39.32099914550781,
                0.8339999914169312
            ],
            "OP2": [
                79.5719985961914,
                -40.367000579833984,
                0.6169999837875366
            ],
            "O5'": [
                81.6259994506836,
                -41.73500061035156,
                0.257999986410141
            ],
            "C5'": [
                82.97799682617188,
                -42.111000061035156,
                0.4699999988079071
            ],
            "C4'": [
                83.28700256347656,
                -43.47100067138672,
                -0.10599999874830246
            ],
            "O4'": [
                82.64600372314453,
                -44.50699996948242,
                0.6869999766349792
            ],
            "C3'": [
                82.79299926757812,
                -43.72600173950195,
                -1.5219999551773071
            ],
            "O3'": [
                83.65299987792969,
                -43.183998107910156,
                -2.509000062942505
            ],
            "C2'": [
                82.68699645996094,
                -45.24399948120117,
                -1.559999942779541
            ],
            "O2'": [
                83.9729995727539,
                -45.827999114990234,
                -1.684000015258789
            ],
            "C1'": [
                82.1719970703125,
                -45.5359992980957,
                -0.15299999713897705
            ],
            "N1": [
                80.68900299072266,
                -45.53900146484375,
                -0.10599999874830246
            ],
            "C2": [
                80.0260009765625,
                -46.67399978637695,
                -0.5320000052452087
            ],
            "O2": [
                80.60299682617188,
                -47.66600036621094,
                -0.9229999780654907
            ],
            "N3": [
                78.65599822998047,
                -46.61600112915039,
                -0.4790000021457672
            ],
            "C4": [
                77.88899993896484,
                -45.555999755859375,
                -0.04699999839067459
            ],
            "O4": [
                76.66500091552734,
                -45.65700149536133,
                -0.05299999937415123
            ],
            "C5": [
                78.63999938964844,
                -44.41299819946289,
                0.3790000081062317
            ],
            "C6": [
                79.97599792480469,
                -44.44300079345703,
                0.3319999873638153
            ]
        },
        "2585": {
            "P": [
                83.08399963378906,
                -42.630001068115234,
                -3.9089999198913574
            ],
            "OP1": [
                84.25399780273438,
                -42.090999603271484,
                -4.646999835968018
            ],
            "OP2": [
                81.91300201416016,
                -41.750999450683594,
                -3.671999931335449
            ],
            "O5'": [
                82.62100219726562,
                -43.93199920654297,
                -4.703000068664551
            ],
            "C5'": [
                82.21800231933594,
                -43.847999572753906,
                -6.066999912261963
            ],
            "C4'": [
                80.94000244140625,
                -44.61000061035156,
                -6.326000213623047
            ],
            "O4'": [
                81.15899658203125,
                -46.025001525878906,
                -6.058000087738037
            ],
            "C3'": [
                79.74800109863281,
                -44.20100021362305,
                -5.456999778747559
            ],
            "O3'": [
                78.53800201416016,
                -44.41999816894531,
                -6.184999942779541
            ],
            "C2'": [
                79.82099914550781,
                -45.2140007019043,
                -4.324999809265137
            ],
            "O2'": [
                78.625,
                -45.37799835205078,
                -3.5950000286102295
            ],
            "C1'": [
                80.21900177001953,
                -46.465999603271484,
                -5.0970001220703125
            ],
            "N1": [
                80.83300018310547,
                -47.51100158691406,
                -4.2769999504089355
            ],
            "C2": [
                79.97899627685547,
                -48.42900085449219,
                -3.7079999446868896
            ],
            "O2": [
                78.77200317382812,
                -48.39400100708008,
                -3.8580000400543213
            ],
            "N3": [
                80.59600067138672,
                -49.37900161743164,
                -2.937999963760376
            ],
            "C4": [
                81.9520034790039,
                -49.50199890136719,
                -2.7070000171661377
            ],
            "O4": [
                82.3550033569336,
                -50.409000396728516,
                -1.9830000400543213
            ],
            "C5": [
                82.76699829101562,
                -48.513999938964844,
                -3.3440001010894775
            ],
            "C6": [
                82.19200134277344,
                -47.57400131225586,
                -4.0960001945495605
            ]
        },
        "2586": {
            "P": [
                77.68599700927734,
                -43.191001892089844,
                -6.763999938964844
            ],
            "OP1": [
                78.55999755859375,
                -41.994998931884766,
                -6.8480000495910645
            ],
            "OP2": [
                76.4020004272461,
                -43.12900161743164,
                -6.03000020980835
            ],
            "O5'": [
                77.31600189208984,
                -43.65599822998047,
                -8.23799991607666
            ],
            "C5'": [
                78.3219985961914,
                -44.04800033569336,
                -9.152999877929688
            ],
            "C4'": [
                77.71900177001953,
                -44.323001861572266,
                -10.498000144958496
            ],
            "O4'": [
                77.03800201416016,
                -45.604000091552734,
                -10.472000122070312
            ],
            "C3'": [
                76.63500213623047,
                -43.347999572753906,
                -10.89799976348877
            ],
            "O3'": [
                77.1259994506836,
                -42.124000549316406,
                -11.39799976348877
            ],
            "C2'": [
                75.80799865722656,
                -44.154998779296875,
                -11.880000114440918
            ],
            "O2'": [
                76.46700286865234,
                -44.244998931884766,
                -13.135000228881836
            ],
            "C1'": [
                75.83300018310547,
                -45.52399826049805,
                -11.206000328063965
            ],
            "N1": [
                74.697998046875,
                -45.67900085449219,
                -10.26099967956543
            ],
            "C2": [
                73.39900207519531,
                -45.87900161743164,
                -10.75100040435791
            ],
            "O2": [
                73.22200012207031,
                -45.93000030517578,
                -11.973999977111816
            ],
            "N3": [
                72.36000061035156,
                -46.01499938964844,
                -9.888999938964844
            ],
            "C4": [
                72.5790023803711,
                -45.94599914550781,
                -8.57800006866455
            ],
            "N4": [
                71.53800201416016,
                -46.07600021362305,
                -7.752999782562256
            ],
            "C5": [
                73.89099884033203,
                -45.75699996948242,
                -8.055000305175781
            ],
            "C6": [
                74.90699768066406,
                -45.63100051879883,
                -8.913999557495117
            ]
        },
        "2587": {
            "P": [
                76.41400146484375,
                -40.78300094604492,
                -10.906999588012695
            ],
            "OP1": [
                77.3010025024414,
                -39.61000061035156,
                -11.081999778747559
            ],
            "OP2": [
                75.89800262451172,
                -41.12900161743164,
                -9.562999725341797
            ],
            "O5'": [
                75.14099884033203,
                -40.65700149536133,
                -11.86299991607666
            ],
            "C5'": [
                75.2229995727539,
                -40.926998138427734,
                -13.255999565124512
            ],
            "C4'": [
                73.87100219726562,
                -41.242000579833984,
                -13.842000007629395
            ],
            "O4'": [
                73.37100219726562,
                -42.47700119018555,
                -13.262999534606934
            ],
            "C3'": [
                72.75900268554688,
                -40.22800064086914,
                -13.574999809265137
            ],
            "O3'": [
                72.7750015258789,
                -39.095001220703125,
                -14.444000244140625
            ],
            "C2'": [
                71.50399780273438,
                -41.08000183105469,
                -13.697999954223633
            ],
            "O2'": [
                71.20099639892578,
                -41.30799865722656,
                -15.067000389099121
            ],
            "C1'": [
                71.97599792480469,
                -42.39500045776367,
                -13.074999809265137
            ],
            "N9": [
                71.69100189208984,
                -42.44200134277344,
                -11.625
            ],
            "C8": [
                72.53099822998047,
                -42.25400161743164,
                -10.550999641418457
            ],
            "N7": [
                71.93800354003906,
                -42.35300064086914,
                -9.385000228881836
            ],
            "C5": [
                70.61900329589844,
                -42.625999450683594,
                -9.701000213623047
            ],
            "C6": [
                69.46099853515625,
                -42.8489990234375,
                -8.923999786376953
            ],
            "N6": [
                69.40599822998047,
                -42.845001220703125,
                -7.589000225067139
            ],
            "N1": [
                68.31199645996094,
                -43.09299850463867,
                -9.586999893188477
            ],
            "C2": [
                68.3219985961914,
                -43.106998443603516,
                -10.92300033569336
            ],
            "N3": [
                69.33699798583984,
                -42.91600036621094,
                -11.755999565124512
            ],
            "C4": [
                70.46299743652344,
                -42.68000030517578,
                -11.076000213623047
            ]
        }
    }
}