{
    "1A": {
        "2576": {
            "P": [
                78.83999633789062,
                -61.362998962402344,
                6.132999897003174
            ],
            "OP1": [
                79.53500366210938,
                -61.94499969482422,
                4.939000129699707
            ],
            "OP2": [
                79.62799835205078,
                -60.303001403808594,
                6.723999977111816
            ],
            "O5'": [
                77.54299926757812,
                -60.45500183105469,
                6.038000106811523
            ],
            "C5'": [
                76.30400085449219,
                -60.73099899291992,
                6.675000190734863
            ],
            "C4'": [
                75.18699645996094,
                -60.21699905395508,
                5.796999931335449
            ],
            "O4'": [
                75.38200378417969,
                -58.80099868774414,
                5.585999965667725
            ],
            "C3'": [
                75.18900299072266,
                -60.845001220703125,
                4.40500020980835
            ],
            "O3'": [
                74.25499725341797,
                -61.86399841308594,
                4.28000020980835
            ],
            "C2'": [
                74.88300323486328,
                -59.722999572753906,
                3.430999994277954
            ],
            "O2'": [
                73.57599639892578,
                -59.84000015258789,
                2.885999917984009
            ],
            "C1'": [
                75.04900360107422,
                -58.45199966430664,
                4.265999794006348
            ],
            "N9": [
                76.08599853515625,
                -57.584999084472656,
                3.7239999771118164
            ],
            "C8": [
                75.9739990234375,
                -56.237998962402344,
                3.61299991607666
            ],
            "N7": [
                77.00199890136719,
                -55.64699935913086,
                3.1029999256134033
            ],
            "C5": [
                77.84500122070312,
                -56.715999603271484,
                2.8469998836517334
            ],
            "C6": [
                79.15299987792969,
                -56.71799850463867,
                2.296999931335449
            ],
            "O6": [
                79.81999969482422,
                -55.72100067138672,
                1.930999994277954
            ],
            "N1": [
                79.6729965209961,
                -58.01300048828125,
                2.2109999656677246
            ],
            "C2": [
                79.03199768066406,
                -59.11399841308594,
                2.631999969482422
            ],
            "N2": [
                79.68299865722656,
                -60.25899887084961,
                2.4709999561309814
            ],
            "N3": [
                77.83599853515625,
                -59.11000061035156,
                3.1559998989105225
            ],
            "C4": [
                77.2969970703125,
                -57.90599822998047,
                3.2339999675750732
            ]
        },
        "2577": {
            "P": [
                74.71299743652344,
                -63.266998291015625,
                3.6989998817443848
            ],
            "OP1": [
                75.51399993896484,
                -63.659000396728516,
                4.835999965667725
            ],
            "OP2": [
                75.2239990234375,
                -63.314998626708984,
                2.2880001068115234
            ],
            "O5'": [
                73.38400268554688,
                -64.12999725341797,
                3.694999933242798
            ],
            "C5'": [
                72.25499725341797,
                -63.59400177001953,
                3.0220000743865967
            ],
            "C4'": [
                71.4010009765625,
                -64.68699645996094,
                2.5250000953674316
            ],
            "O4'": [
                72.125,
                -65.4219970703125,
                1.5230000019073486
            ],
            "C3'": [
                71.14700317382812,
                -65.71199798583984,
                3.5810000896453857
            ],
            "O3'": [
                70.14800262451172,
                -65.29399871826172,
                4.4720001220703125
            ],
            "C2'": [
                70.78299713134766,
                -66.91100311279297,
                2.753999948501587
            ],
            "O2'": [
                69.48699951171875,
                -66.68399810791016,
                2.2160000801086426
            ],
            "C1'": [
                71.79900360107422,
                -66.77999877929688,
                1.6200000047683716
            ],
            "N9": [
                73.03199768066406,
                -67.54900360107422,
                1.8320000171661377
            ],
            "C8": [
                74.21499633789062,
                -67.13700103759766,
                2.36899995803833
            ],
            "N7": [
                75.17400360107422,
                -68.06600189208984,
                2.427000045776367
            ],
            "C5": [
                74.54499816894531,
                -69.16100311279297,
                1.8630000352859497
            ],
            "C6": [
                75.01499938964844,
                -70.46600341796875,
                1.5989999771118164
            ],
            "N6": [
                76.26799774169922,
                -70.87300109863281,
                1.9019999504089355
            ],
            "N1": [
                74.14299774169922,
                -71.3270034790039,
                1.0089999437332153
            ],
            "C2": [
                72.91300201416016,
                -70.86100006103516,
                0.7229999899864197
            ],
            "N3": [
                72.35900115966797,
                -69.66699981689453,
                0.9330000281333923
            ],
            "C4": [
                73.23699951171875,
                -68.8499984741211,
                1.5019999742507935
            ]
        },
        "2578": {
            "P": [
                69.9520034790039,
                -66.0530014038086,
                5.861000061035156
            ],
            "OP1": [
                69.81300354003906,
                -67.4530029296875,
                5.460999965667725
            ],
            "OP2": [
                68.88300323486328,
                -65.40299987792969,
                6.668000221252441
            ],
            "O5'": [
                71.33399963378906,
                -65.86199951171875,
                6.616000175476074
            ],
            "C5'": [
                71.98600006103516,
                -64.60800170898438,
                6.695000171661377
            ],
            "C4'": [
                71.43099975585938,
                -63.7869987487793,
                7.814000129699707
            ],
            "O4'": [
                72.16300201416016,
                -63.96099853515625,
                9.053999900817871
            ],
            "C3'": [
                71.49500274658203,
                -62.319000244140625,
                7.565000057220459
            ],
            "O3'": [
                70.48899841308594,
                -61.97100067138672,
                6.666999816894531
            ],
            "C2'": [
                71.31700134277344,
                -61.75,
                8.95199966430664
            ],
            "O2'": [
                69.947998046875,
                -61.74599838256836,
                9.288000106811523
            ],
            "C1'": [
                72.09100341796875,
                -62.78099822998047,
                9.807000160217285
            ],
            "N9": [
                73.45899963378906,
                -62.290000915527344,
                10.069999694824219
            ],
            "C8": [
                74.6709976196289,
                -62.66600036621094,
                9.597000122070312
            ],
            "N7": [
                75.61000061035156,
                -61.888999938964844,
                10.017999649047852
            ],
            "C5": [
                74.99700164794922,
                -60.926998138427734,
                10.777999877929688
            ],
            "C6": [
                75.4540023803711,
                -59.7859992980957,
                11.494000434875488
            ],
            "O6": [
                76.5999984741211,
                -59.38999938964844,
                11.604999542236328
            ],
            "N1": [
                74.48400115966797,
                -59.04800033569336,
                12.156999588012695
            ],
            "C2": [
                73.14700317382812,
                -59.391998291015625,
                12.11299991607666
            ],
            "N2": [
                72.19000244140625,
                -58.650001525878906,
                12.765999794006348
            ],
            "N3": [
                72.72899627685547,
                -60.46900177001953,
                11.437000274658203
            ],
            "C4": [
                73.68800354003906,
                -61.18000030517578,
                10.8100004196167
            ]
        },
        "2579": {
            "P": [
                70.43699645996094,
                -60.5359992980957,
                5.993000030517578
            ],
            "OP1": [
                69.3479995727539,
                -60.61800003051758,
                4.9629998207092285
            ],
            "OP2": [
                71.77300262451172,
                -60.0629997253418,
                5.576000213623047
            ],
            "O5'": [
                70.06099700927734,
                -59.57699966430664,
                7.196000099182129
            ],
            "C5'": [
                68.72899627685547,
                -59.21799850463867,
                7.413000106811523
            ],
            "C4'": [
                68.66500091552734,
                -58.207000732421875,
                8.486000061035156
            ],
            "O4'": [
                69.5719985961914,
                -58.58399963378906,
                9.538999557495117
            ],
            "C3'": [
                69.13099670410156,
                -56.827999114990234,
                8.105999946594238
            ],
            "O3'": [
                68.16699981689453,
                -56.08700180053711,
                7.431000232696533
            ],
            "C2'": [
                69.41699981689453,
                -56.242000579833984,
                9.456999778747559
            ],
            "O2'": [
                68.2040023803711,
                -55.99599838256836,
                10.156999588012695
            ],
            "C1'": [
                70.12100219726562,
                -57.4119987487793,
                10.111000061035156
            ],
            "N1": [
                71.56300354003906,
                -57.314998626708984,
                9.788999557495117
            ],
            "C2": [
                72.3290023803711,
                -56.297000885009766,
                10.364999771118164
            ],
            "O2": [
                71.79900360107422,
                -55.527000427246094,
                11.178999900817871
            ],
            "N3": [
                73.63400268554688,
                -56.183998107910156,
                10.034000396728516
            ],
            "C4": [
                74.15299987792969,
                -57.03499984741211,
                9.182000160217285
            ],
            "N4": [
                75.40499877929688,
                -56.935001373291016,
                8.843999862670898
            ],
            "C5": [
                73.41000366210938,
                -58.051998138427734,
                8.5600004196167
            ],
            "C6": [
                72.12100219726562,
                -58.152000427246094,
                8.878999710083008
            ]
        },
        "2580": {
            "P": [
                68.53700256347656,
                -55.40599822998047,
                6.048999786376953
            ],
            "OP1": [
                67.28299713134766,
                -55.12300109863281,
                5.309000015258789
            ],
            "OP2": [
                69.61199951171875,
                -56.18000030517578,
                5.363999843597412
            ],
            "O5'": [
                69.0,
                -53.98500061035156,
                6.540999889373779
            ],
            "C5'": [
                68.29900360107422,
                -53.32899856567383,
                7.566999912261963
            ],
            "C4'": [
                69.25700378417969,
                -52.53799819946289,
                8.420000076293945
            ],
            "O4'": [
                70.37300109863281,
                -53.362998962402344,
                8.79800033569336
            ],
            "C3'": [
                69.9010009765625,
                -51.30400085449219,
                7.803999900817871
            ],
            "O3'": [
                69.0469970703125,
                -50.18600082397461,
                7.942999839782715
            ],
            "C2'": [
                71.14700317382812,
                -51.12200164794922,
                8.652000427246094
            ],
            "O2'": [
                70.76200103759766,
                -50.47600173950195,
                9.848999977111816
            ],
            "C1'": [
                71.50599670410156,
                -52.564998626708984,
                9.015000343322754
            ],
            "N1": [
                72.62100219726562,
                -53.14699935913086,
                8.23799991607666
            ],
            "C2": [
                73.81999969482422,
                -52.54499816894531,
                8.347000122070312
            ],
            "O2": [
                73.95999908447266,
                -51.551998138427734,
                9.015999794006348
            ],
            "N3": [
                74.81400299072266,
                -53.12799835205078,
                7.629000186920166
            ],
            "C4": [
                74.78199768066406,
                -54.23699951171875,
                6.836999893188477
            ],
            "O4": [
                75.83000183105469,
                -54.60900115966797,
                6.264999866485596
            ],
            "C5": [
                73.4990005493164,
                -54.840999603271484,
                6.800000190734863
            ],
            "C6": [
                72.5,
                -54.301998138427734,
                7.489999771118164
            ]
        },
        "2581": {
            "P": [
                68.31300354003906,
                -49.529998779296875,
                6.696000099182129
            ],
            "OP1": [
                67.62000274658203,
                -48.388999938964844,
                7.336999893188477
            ],
            "OP2": [
                67.60600280761719,
                -50.51599884033203,
                5.85699987411499
            ],
            "O5'": [
                69.50499725341797,
                -48.8489990234375,
                5.934000015258789
            ],
            "C5'": [
                70.20700073242188,
                -47.880001068115234,
                6.665999889373779
            ],
            "C4'": [
                71.5469970703125,
                -47.63999938964844,
                6.086999893188477
            ],
            "O4'": [
                72.31900024414062,
                -48.875,
                6.1539998054504395
            ],
            "C3'": [
                71.52799987792969,
                -47.20000076293945,
                4.625
            ],
            "O3'": [
                72.48200225830078,
                -46.15399932861328,
                4.432000160217285
            ],
            "C2'": [
                71.98300170898438,
                -48.45500183105469,
                3.878999948501587
            ],
            "O2'": [
                72.61199951171875,
                -48.20500183105469,
                2.628000020980835
            ],
            "C1'": [
                72.93800354003906,
                -49.07699966430664,
                4.9070000648498535
            ],
            "N9": [
                73.25399780273438,
                -50.481998443603516,
                4.672999858856201
            ],
            "C8": [
                74.51000213623047,
                -50.98400115966797,
                4.513999938964844
            ],
            "N7": [
                74.56999969482422,
                -52.25199890136719,
                4.250999927520752
            ],
            "C5": [
                73.23200225830078,
                -52.5989990234375,
                4.210999965667725
            ],
            "C6": [
                72.61499786376953,
                -53.8489990234375,
                3.930999994277954
            ],
            "O6": [
                73.15699768066406,
                -54.926998138427734,
                3.671999931335449
            ],
            "N1": [
                71.22200012207031,
                -53.803001403808594,
                3.9719998836517334
            ],
            "C2": [
                70.49700164794922,
                -52.68199920654297,
                4.241000175476074
            ],
            "N2": [
                69.15899658203125,
                -52.862998962402344,
                4.228000164031982
            ],
            "N3": [
                71.05999755859375,
                -51.48899841308594,
                4.492000102996826
            ],
            "C4": [
                72.41400146484375,
                -51.518001556396484,
                4.453999996185303
            ]
        },
        "2582": {
            "P": [
                72.01300048828125,
                -44.637001037597656,
                4.172999858856201
            ],
            "OP1": [
                70.56099700927734,
                -44.457000732421875,
                4.0970001220703125
            ],
            "OP2": [
                72.75700378417969,
                -44.1870002746582,
                2.996999979019165
            ],
            "O5'": [
                72.29399871826172,
                -43.926998138427734,
                5.554999828338623
            ],
            "C5'": [
                72.54100036621094,
                -42.54800033569336,
                5.623000144958496
            ],
            "C4'": [
                73.65699768066406,
                -42.2859992980957,
                6.591000080108643
            ],
            "O4'": [
                73.625,
                -43.266998291015625,
                7.672999858856201
            ],
            "C3'": [
                75.05400085449219,
                -42.435001373291016,
                6.0279998779296875
            ],
            "O3'": [
                75.46800231933594,
                -41.332000732421875,
                5.260000228881836
            ],
            "C2'": [
                75.85299682617188,
                -42.612998962402344,
                7.281000137329102
            ],
            "O2'": [
                75.82099914550781,
                -41.37799835205078,
                7.9629998207092285
            ],
            "C1'": [
                74.95500183105469,
                -43.57899856567383,
                8.053000450134277
            ],
            "N9": [
                75.22100067138672,
                -44.992000579833984,
                7.697999954223633
            ],
            "C8": [
                74.23999786376953,
                -45.941001892089844,
                7.5
            ],
            "N7": [
                74.64800262451172,
                -47.137001037597656,
                7.150000095367432
            ],
            "C5": [
                76.00499725341797,
                -46.959999084472656,
                7.10099983215332
            ],
            "C6": [
                76.98699951171875,
                -47.90700149536133,
                6.770999908447266
            ],
            "O6": [
                76.86000061035156,
                -49.071998596191406,
                6.460999965667725
            ],
            "N1": [
                78.2490005493164,
                -47.400001525878906,
                6.815999984741211
            ],
            "C2": [
                78.51399993896484,
                -46.13199996948242,
                7.140999794006348
            ],
            "N2": [
                79.80999755859375,
                -45.89099884033203,
                7.0920000076293945
            ],
            "N3": [
                77.62300109863281,
                -45.21200180053711,
                7.4730000495910645
            ],
            "C4": [
                76.37999725341797,
                -45.67499923706055,
                7.440999984741211
            ]
        },
        "2583": {
            "P": [
                75.4990005493164,
                -41.46099853515625,
                3.6600000858306885
            ],
            "OP1": [
                74.56099700927734,
                -40.55500030517578,
                2.928999900817871
            ],
            "OP2": [
                75.39700317382812,
                -42.89799880981445,
                3.3399999141693115
            ],
            "O5'": [
                76.99199676513672,
                -41.108001708984375,
                3.309999942779541
            ],
            "C5'": [
                77.89600372314453,
                -40.845001220703125,
                4.354000091552734
            ],
            "C4'": [
                79.0989990234375,
                -41.73699951171875,
                4.309000015258789
            ],
            "O4'": [
                78.76599884033203,
                -43.020999908447266,
                4.829999923706055
            ],
            "C3'": [
                79.69999694824219,
                -42.05799865722656,
                2.9570000171661377
            ],
            "O3'": [
                80.45800018310547,
                -40.99399948120117,
                2.4149999618530273
            ],
            "C2'": [
                80.55000305175781,
                -43.27000045776367,
                3.2869999408721924
            ],
            "O2'": [
                81.78199768066406,
                -42.90399932861328,
                3.9049999713897705
            ],
            "C1'": [
                79.69000244140625,
                -43.95800018310547,
                4.3429999351501465
            ],
            "N9": [
                79.02100372314453,
                -45.17100143432617,
                3.8540000915527344
            ],
            "C8": [
                77.71600341796875,
                -45.56999969482422,
                3.825000047683716
            ],
            "N7": [
                77.55400085449219,
                -46.77299880981445,
                3.3350000381469727
            ],
            "C5": [
                78.84200286865234,
                -47.176998138427734,
                3.058000087738037
            ],
            "C6": [
                79.33200073242188,
                -48.367000579833984,
                2.506999969482422
            ],
            "O6": [
                78.69000244140625,
                -49.354000091552734,
                2.1679999828338623
            ],
            "N1": [
                80.71299743652344,
                -48.34299850463867,
                2.38100004196167
            ],
            "C2": [
                81.52799987792969,
                -47.279998779296875,
                2.747999906539917
            ],
            "N2": [
                82.86900329589844,
                -47.34700012207031,
                2.559999942779541
            ],
            "N3": [
                81.06700134277344,
                -46.178001403808594,
                3.2730000019073486
            ],
            "C4": [
                79.73799896240234,
                -46.20600128173828,
                3.384000062942505
            ]
        },
        "2584": {
            "P": [
                80.31900024414062,
                -40.555999755859375,
                0.875
            ],
            "OP1": [
                81.00299835205078,
                -39.2400016784668,
                0.9300000071525574
            ],
            "OP2": [
                78.93800354003906,
                -40.60900115966797,
                0.33500000834465027
            ],
            "O5'": [
                81.13800048828125,
                -41.66400146484375,
                0.07400000095367432
            ],
            "C5'": [
                82.55699920654297,
                -41.6609992980957,
                0.035999998450279236
            ],
            "C4'": [
                83.11199951171875,
                -42.97999954223633,
                -0.4569999873638153
            ],
            "O4'": [
                82.65399932861328,
                -44.077999114990234,
                0.39399999380111694
            ],
            "C3'": [
                82.66600036621094,
                -43.426998138427734,
                -1.8270000219345093
            ],
            "O3'": [
                83.24700164794922,
                -42.768001556396484,
                -2.9089999198913574
            ],
            "C2'": [
                82.95800018310547,
                -44.90999984741211,
                -1.7879999876022339
            ],
            "O2'": [
                84.36100006103516,
                -45.12200164794922,
                -1.8079999685287476
            ],
            "C1'": [
                82.43399810791016,
                -45.237998962402344,
                -0.40299999713897705
            ],
            "N1": [
                80.96800231933594,
                -45.569000244140625,
                -0.39800000190734863
            ],
            "C2": [
                80.45099639892578,
                -46.680999755859375,
                -1.0859999656677246
            ],
            "O2": [
                81.15699768066406,
                -47.40800094604492,
                -1.7599999904632568
            ],
            "N3": [
                79.06900024414062,
                -46.91299819946289,
                -0.972000002861023
            ],
            "C4": [
                78.12300109863281,
                -46.16600036621094,
                -0.24199999868869781
            ],
            "O4": [
                76.90399932861328,
                -46.4640007019043,
                -0.21799999475479126
            ],
            "C5": [
                78.72599792480469,
                -45.04399871826172,
                0.44999998807907104
            ],
            "C6": [
                80.06099700927734,
                -44.80799865722656,
                0.3479999899864197
            ]
        },
        "2585": {
            "P": [
                82.38700103759766,
                -42.803001403808594,
                -4.251999855041504
            ],
            "OP1": [
                83.072998046875,
                -43.650001525878906,
                -5.25600004196167
            ],
            "OP2": [
                81.97799682617188,
                -41.382999420166016,
                -4.584000110626221
            ],
            "O5'": [
                81.16799926757812,
                -43.75400161743164,
                -3.8239998817443848
            ],
            "C5'": [
                81.06999969482422,
                -45.0890007019043,
                -4.310999870300293
            ],
            "C4'": [
                80.40399932861328,
                -45.08000183105469,
                -5.644999980926514
            ],
            "O4'": [
                81.2969970703125,
                -45.665000915527344,
                -6.63700008392334
            ],
            "C3'": [
                79.06099700927734,
                -45.81700134277344,
                -5.7179999351501465
            ],
            "O3'": [
                77.9469985961914,
                -44.944000244140625,
                -5.989999771118164
            ],
            "C2'": [
                79.26899719238281,
                -46.915000915527344,
                -6.796000003814697
            ],
            "O2'": [
                78.18199920654297,
                -47.12300109863281,
                -7.695000171661377
            ],
            "C1'": [
                80.56700134277344,
                -46.48899841308594,
                -7.5279998779296875
            ],
            "N1": [
                81.41500091552734,
                -47.652000427246094,
                -7.9120001792907715
            ],
            "C2": [
                81.4209976196289,
                -48.0989990234375,
                -9.265000343322754
            ],
            "O2": [
                80.81099700927734,
                -47.569000244140625,
                -10.208999633789062
            ],
            "N3": [
                82.19999694824219,
                -49.215999603271484,
                -9.494999885559082
            ],
            "C4": [
                82.93099975585938,
                -49.87699890136719,
                -8.553000450134277
            ],
            "O4": [
                83.52300262451172,
                -50.82600021362305,
                -8.961000442504883
            ],
            "C5": [
                82.90599822998047,
                -49.4109992980957,
                -7.203999996185303
            ],
            "C6": [
                82.14199829101562,
                -48.340999603271484,
                -6.934000015258789
            ]
        },
        "2586": {
            "P": [
                78.01599884033203,
                -43.64799880981445,
                -6.960999965667725
            ],
            "OP1": [
                79.35199737548828,
                -43.055999755859375,
                -7.23199987411499
            ],
            "OP2": [
                76.94400024414062,
                -42.689998626708984,
                -6.526000022888184
            ],
            "O5'": [
                77.61100006103516,
                -44.229000091552734,
                -8.369999885559082
            ],
            "C5'": [
                78.30699920654297,
                -43.77799987792969,
                -9.501999855041504
            ],
            "C4'": [
                77.58300018310547,
                -44.13199996948242,
                -10.751999855041504
            ],
            "O4'": [
                76.93299865722656,
                -45.40399932861328,
                -10.576000213623047
            ],
            "C3'": [
                76.45899963378906,
                -43.220001220703125,
                -11.10099983215332
            ],
            "O3'": [
                76.88099670410156,
                -42.00199890136719,
                -11.628000259399414
            ],
            "C2'": [
                75.64900207519531,
                -44.07600021362305,
                -12.024999618530273
            ],
            "O2'": [
                76.31800079345703,
                -44.21099853515625,
                -13.256999969482422
            ],
            "C1'": [
                75.7300033569336,
                -45.4109992980957,
                -11.284000396728516
            ],
            "N1": [
                74.66799926757812,
                -45.507999420166016,
                -10.28499984741211
            ],
            "C2": [
                73.3949966430664,
                -45.667999267578125,
                -10.725000381469727
            ],
            "O2": [
                73.25,
                -45.757999420166016,
                -11.942000389099121
            ],
            "N3": [
                72.38700103759766,
                -45.70500183105469,
                -9.852999687194824
            ],
            "C4": [
                72.66300201416016,
                -45.55099868774414,
                -8.579000473022461
            ],
            "N4": [
                71.6760025024414,
                -45.58000183105469,
                -7.696000099182129
            ],
            "C5": [
                73.96600341796875,
                -45.380001068115234,
                -8.104999542236328
            ],
            "C6": [
                74.94100189208984,
                -45.36600112915039,
                -8.991000175476074
            ]
        },
        "2587": {
            "P": [
                76.20700073242188,
                -40.72100067138672,
                -10.980999946594238
            ],
            "OP1": [
                77.00199890136719,
                -39.47999954223633,
                -10.909000396728516
            ],
            "OP2": [
                75.87200164794922,
                -41.275001525878906,
                -9.680000305175781
            ],
            "O5'": [
                74.91200256347656,
                -40.527000427246094,
                -11.892000198364258
            ],
            "C5'": [
                74.99800109863281,
                -40.61899948120117,
                -13.324000358581543
            ],
            "C4'": [
                73.68900299072266,
                -41.00600051879883,
                -13.980999946594238
            ],
            "O4'": [
                73.18900299072266,
                -42.22600173950195,
                -13.354999542236328
            ],
            "C3'": [
                72.57099914550781,
                -40.00400161743164,
                -13.776000022888184
            ],
            "O3'": [
                72.61299896240234,
                -38.858001708984375,
                -14.630000114440918
            ],
            "C2'": [
                71.30599975585938,
                -40.856998443603516,
                -13.829000473022461
            ],
            "O2'": [
                70.89900207519531,
                -41.12099838256836,
                -15.17300033569336
            ],
            "C1'": [
                71.79299926757812,
                -42.150001525878906,
                -13.180999755859375
            ],
            "N9": [
                71.52899932861328,
                -42.16999816894531,
                -11.75
            ],
            "C8": [
                72.41699981689453,
                -41.965999603271484,
                -10.73799991607666
            ],
            "N7": [
                71.90499877929688,
                -42.08000183105469,
                -9.529000282287598
            ],
            "C5": [
                70.58599853515625,
                -42.39500045776367,
                -9.79699993133545
            ],
            "C6": [
                69.51000213623047,
                -42.62300109863281,
                -8.947999954223633
            ],
            "N6": [
                69.58100128173828,
                -42.566001892089844,
                -7.619999885559082
            ],
            "N1": [
                68.34100341796875,
                -42.909000396728516,
                -9.520999908447266
            ],
            "C2": [
                68.31500244140625,
                -42.94300079345703,
                -10.85200023651123
            ],
            "N3": [
                69.25199890136719,
                -42.72999954223633,
                -11.76200008392334
            ],
            "C4": [
                70.36399841308594,
                -42.446998596191406,
                -11.151000022888184
            ]
        }
    }
}